pymrs/__init__.py
pymrs/__version__.py
pymrs/asyncclient.py
pymrs/client.py
pymrs/data_requests.py
pymrs/exceptions.py
pymrs-0.3.7.dist-info/METADATA
pymrs-0.3.7.dist-info/WHEEL
pymrs-0.3.7.dist-info/licenses/LICENSE
pymrs-0.3.7.dist-info/RECORD
