Metadata-Version: 2.4
Name: pymrs
Version: 0.3.7
Summary: Python SDK for MRS.
Author-email: Artyom Tyurin <arty@search-centric.ru>
Maintainer-email: Artyom Tyurin <arty@search-centric.ru>
License: BSD Zero Clause License
License-File: LICENSE
Classifier: Development Status :: 3 - Alpha
Classifier: Intended Audience :: Developers
Classifier: License :: OSI Approved :: BSD License
Classifier: Operating System :: OS Independent
Classifier: Programming Language :: Python :: 3
Classifier: Programming Language :: Python :: 3 :: Only
Classifier: Programming Language :: Python :: 3.9
Classifier: Programming Language :: Python :: 3.10
Classifier: Programming Language :: Python :: 3.11
Classifier: Programming Language :: Python :: 3.12
Classifier: Topic :: Software Development :: Libraries :: Python Modules
Requires-Python: >=3.9
